[{"name":"abstract fun read(buffer: ByteArray, offset: Int = 0, max: Int = buffer.size - offset): Int","description":"io.klibs.io.ByteReader.read","location":"io-stream/io.klibs.io/-byte-reader/read.html","searchKeys":["read","abstract fun read(buffer: ByteArray, offset: Int = 0, max: Int = buffer.size - offset): Int","io.klibs.io.ByteReader.read"]},{"name":"abstract fun write(buffer: ByteArray, offset: Int = 0, len: Int = buffer.size - offset)","description":"io.klibs.io.ByteWriter.write","location":"io-stream/io.klibs.io/-byte-writer/write.html","searchKeys":["write","abstract fun write(buffer: ByteArray, offset: Int = 0, len: Int = buffer.size - offset)","io.klibs.io.ByteWriter.write"]},{"name":"interface ByteReader","description":"io.klibs.io.ByteReader","location":"io-stream/io.klibs.io/-byte-reader/index.html","searchKeys":["ByteReader","interface ByteReader","io.klibs.io.ByteReader"]},{"name":"interface ByteWriter","description":"io.klibs.io.ByteWriter","location":"io-stream/io.klibs.io/-byte-writer/index.html","searchKeys":["ByteWriter","interface ByteWriter","io.klibs.io.ByteWriter"]}]
